insightx/__init__.py
insightx/_modidx.py
insightx/core.py
insightx/jupyterutils.py
insightx/osutils.py
insightx-0.0.3.dist-info/LICENSE
insightx-0.0.3.dist-info/METADATA
insightx-0.0.3.dist-info/WHEEL
insightx-0.0.3.dist-info/entry_points.txt
insightx-0.0.3.dist-info/top_level.txt
insightx-0.0.3.dist-info/RECORD
