Metadata-Version: 2.1
Name: insightx
Version: 0.0.3
Summary: a thin wrapper for powerful data science packages
Home-page: https://github.com/HaveF/insightx
Author: HaveF
Author-email: iamaplayer@gmail.com
License: Apache Software License 2.0
Keywords: nbdev jupyter notebook python
Platform: UNKNOWN
Classifier: Development Status :: 4 - Beta
Classifier: Intended Audience :: Developers
Classifier: Natural Language :: English
Classifier: Programming Language :: Python :: 3.9
Classifier: Programming Language :: Python :: 3.10
Classifier: License :: OSI Approved :: Apache Software License
Requires-Python: >=3.9
License-File: LICENSE
Requires-Dist: pandas
Requires-Dist: polars
Requires-Dist: numpy
Requires-Dist: IPython
Requires-Dist: seaborn
Requires-Dist: jinja2
Provides-Extra: dev
